README.md
setup.py
aios_part_uploader/__init__.py
aios_part_uploader/cs.py
aios_part_uploader/dp.py
aios_part_uploader/exceptions.py
aios_part_uploader.egg-info/PKG-INFO
aios_part_uploader.egg-info/SOURCES.txt
aios_part_uploader.egg-info/dependency_links.txt
aios_part_uploader.egg-info/top_level.txt