Metadata-Version: 1.0
Name: aios-part-uploader
Version: 0.0.16
Summary: aios part uploader
Home-page: https://github.com/wangxiao1427/python_helper/tree/master/aios_part_uploader
Author: shawn_wg
Author-email: wang.xiao@intellif.com
License: MIT Licence
Keywords: aios,part,uploader
Platform: any
